cobolio/CopybookParser.py
cobolio/CopybookTokenizer.py
cobolio/__init__.py
cobolio/config.py
cobolio/parser.py
cobolio/cli/__init__.py
cobolio/cli/cob_to_csv.py
cobolio-0.1.5.dist-info/LICENSE
cobolio-0.1.5.dist-info/METADATA
cobolio-0.1.5.dist-info/WHEEL
cobolio-0.1.5.dist-info/entry_points.txt
cobolio-0.1.5.dist-info/top_level.txt
cobolio-0.1.5.dist-info/RECORD
