Metadata-Version: 2.1
Name: cobolio
Version: 0.1.5
Summary: 'Package for working with mainframe COBOL files'
Home-page: https://github.com/adelosa/cobolio
Author: Anthony Delosa
Author-email: adelosa@gmail.com
License: MIT
Classifier: License :: OSI Approved :: MIT License
Classifier: Programming Language :: Python :: 3
Classifier: Programming Language :: Python :: 3.7
Classifier: Programming Language :: Python :: 3.8
Classifier: Programming Language :: Python :: 3.9
Classifier: Programming Language :: Python :: 3.10
Classifier: Programming Language :: Python :: 3.11
License-File: LICENSE
Provides-Extra: docs
Requires-Dist: sphinx ; extra == 'docs'
Requires-Dist: sphinx-rtd-theme ; extra == 'docs'
Provides-Extra: test
Requires-Dist: flake8 ; extra == 'test'
Requires-Dist: pytest ; extra == 'test'
Requires-Dist: bump2version ; extra == 'test'
Requires-Dist: coverage ; extra == 'test'
